weaverun/__init__.py
weaverun/cli.py
weaverun/config.py
weaverun/dashboard.py
weaverun/detect.py
weaverun/proxy.py
weaverun/setup.py
weaverun/trace_context.py
weaverun/upstream.py
weaverun/weave_log.py
weaverun/templates/base.html
weaverun/templates/dashboard.html
weaverun-0.1.2.dist-info/licenses/LICENSE
weaverun-0.1.2.dist-info/METADATA
weaverun-0.1.2.dist-info/WHEEL
weaverun-0.1.2.dist-info/entry_points.txt
weaverun-0.1.2.dist-info/top_level.txt
weaverun-0.1.2.dist-info/RECORD
