Metadata-Version: 2.4
Name: weaverun
Version: 0.1.2
Summary: Run any app and capture LLM API traffic to Weave (OpenAI, Anthropic, Gemini, Bedrock, Azure, and more)
Requires-Python: >=3.9
License-File: LICENSE
Requires-Dist: fastapi
Requires-Dist: uvicorn
Requires-Dist: httpx
Requires-Dist: typer
Requires-Dist: weave
Requires-Dist: python-dotenv
Requires-Dist: pyyaml
Requires-Dist: jinja2
Dynamic: license-file
